ampel/abstract/AbsApplicable.py
ampel/abstract/AbsCLIOperation.py
ampel/abstract/AbsCustomStateT2Unit.py
ampel/abstract/AbsIdMapper.py
ampel/abstract/AbsPointT2Unit.py
ampel/abstract/AbsSecretProvider.py
ampel/abstract/AbsStateT2Unit.py
ampel/abstract/AbsStockT2Unit.py
ampel/abstract/AbsT0Unit.py
ampel/abstract/AbsT1CombineUnit.py
ampel/abstract/AbsT1ComputeUnit.py
ampel/abstract/AbsT1RetroCombineUnit.py
ampel/abstract/AbsT3Unit.py
ampel/abstract/AbsT4Unit.py
ampel/abstract/AbsTiedCustomStateT2Unit.py
ampel/abstract/AbsTiedPointT2Unit.py
ampel/abstract/AbsTiedStateT2Unit.py
ampel/abstract/AbsTiedStockT2Unit.py
ampel/abstract/AbsTiedT2Unit.py
ampel/alert/AmpelAlert.py
ampel/base/AlternativeAmpelBaseModel.py
ampel/base/AmpelABC.py
ampel/base/AmpelBaseModel.py
ampel/base/AmpelFlexModel.py
ampel/base/AmpelGenericModel.py
ampel/base/AmpelUnit.py
ampel/base/AuxUnitRegister.py
ampel/base/BadConfig.py
ampel/base/LogicalUnit.py
ampel/base/decorator.py
ampel/cli/AmpelArgumentParser.py
ampel/cli/AmpelHelpFormatter.py
ampel/cli/ArgParserBuilder.py
ampel/cli/LoadAllOfAction.py
ampel/cli/LoadAnyOfAction.py
ampel/cli/LoadJSONAction.py
ampel/cli/MaybeIntAction.py
ampel/cli/config.py
ampel/cli/main.py
ampel/config/AmpelConfig.py
ampel/content/DataPoint.py
ampel/content/EventDocument.py
ampel/content/JournalRecord.py
ampel/content/LogDocument.py
ampel/content/MetaActivity.py
ampel/content/MetaRecord.py
ampel/content/StockDocument.py
ampel/content/T1Document.py
ampel/content/T2Document.py
ampel/content/T3Document.py
ampel/content/T4Document.py
ampel/enum/DocumentCode.py
ampel/enum/EventCode.py
ampel/enum/JournalActionCode.py
ampel/enum/MetaActionCode.py
ampel/model/DPSelection.py
ampel/model/StateT2Dependency.py
ampel/model/UnitModel.py
ampel/model/operator/AllOf.py
ampel/model/operator/AnyOf.py
ampel/model/operator/FlatAnyOf.py
ampel/model/operator/OneOf.py
ampel/protocol/AmpelAlertProtocol.py
ampel/protocol/LoggerProtocol.py
ampel/protocol/LoggingHandlerProtocol.py
ampel/py.typed
ampel_interface-0.10.4.post2.dist-info/LICENSE
ampel_interface-0.10.4.post2.dist-info/METADATA
ampel_interface-0.10.4.post2.dist-info/WHEEL
ampel_interface-0.10.4.post2.dist-info/RECORD
